README.rst
setup.py
bsnode/__init__.py
bsnode/check.py
bsnode/cli.py
bsnode/entry.py
bsnode/logtool.py
bsnode/ports.py
bsnode/tools.py
bsnode.egg-info/PKG-INFO
bsnode.egg-info/SOURCES.txt
bsnode.egg-info/dependency_links.txt
bsnode.egg-info/entry_points.txt
bsnode.egg-info/requires.txt
bsnode.egg-info/top_level.txt
bsnode/make/__init__.py
bsnode/make/steam/__init__.py
bsnode/make/steam/define.py
bsnode/make/templates/steam_cs_go_node.tpl
bsnode/make/templates/steam_new_node.tpl
bsnode/manage/__init__.py
bsnode/manage/pwd.py
bsnode/manage/rm.py